<annotation>
  <folder>Untitled Folder</folder>
  <filename>51GSE6CarhL._SX268_</filename>
  <path>./51GSE6CarhL._SX268_.jpg</path>
  <source>
    <database>Unknown</database>
  </source>
  <size>
    <width>268</width>
    <height>201</height>
    <depth>3</depth>
  </size>
  <segmented>0</segmented>
  <object>
    <name>smurf</name>
    <pose>Unspecified</pose>
    <truncated>0</truncated>
    <difficult>0</difficult>
    <bndbox>
      <xmin>21</xmin>
      <ymin>16</ymin>
      <xmax>104</xmax>
      <ymax>178</ymax>
    </bndbox>
  </object>
  <object>
    <name>smurf</name>
    <pose>Unspecified</pose>
    <truncated>0</truncated>
    <difficult>0</difficult>
    <bndbox>
      <xmin>141</xmin>
      <ymin>26</ymin>
      <xmax>231</xmax>
      <ymax>188</ymax>
    </bndbox>
  </object>
</annotation>
