<annotation>
  <folder>data</folder>
  <filename>Personality_Switch</filename>
  <path>./Personality_Switch.jpg</path>
  <source>
    <database>Unknown</database>
  </source>
  <size>
    <width>640</width>
    <height>488</height>
    <depth>3</depth>
  </size>
  <segmented>0</segmented>
  <object>
    <name>smurf</name>
    <pose>Unspecified</pose>
    <truncated>0</truncated>
    <difficult>0</difficult>
    <bndbox>
      <xmin>316</xmin>
      <ymin>74</ymin>
      <xmax>528</xmax>
      <ymax>414</ymax>
    </bndbox>
  </object>
  <object>
    <name>smurf</name>
    <pose>Unspecified</pose>
    <truncated>0</truncated>
    <difficult>0</difficult>
    <bndbox>
      <xmin>84</xmin>
      <ymin>77</ymin>
      <xmax>305</xmax>
      <ymax>447</ymax>
    </bndbox>
  </object>
</annotation>
